[{"label":"Maida","value":"1"},{"label":"Refined Oil","value":"2"},{"label":"Salt","value":"3"},{"label":"Raw Chicken","value":"4"},{"label":"Paneer","value":"5"},{"label":"Onion","value":"6"},{"label":"Red Chilli Powder","value":"7"},{"label":"Chicken Masala","value":"8"},{"label":"Cumin Powder ","value":"9"},{"label":"Yogurt","value":"10"},{"label":"Mustard Oil","value":"11"},{"label":"Chilli Flakes","value":"12"},{"label":"Cucumber","value":"14"},{"label":"Raw Mutton","value":"15"},{"label":"Raw Fish","value":"16"},{"label":"Potato","value":"17"},{"label":"Garlic","value":"18"},{"label":"Coriander","value":"19"},{"label":"Jagery","value":"20"},{"label":"Kidney Beans","value":"21"},{"label":"Green Gram","value":"22"},{"label":"Oregano","value":"23"},{"label":"Flour","value":"24"},{"label":"Besan","value":"25"},{"label":"Black Pepper","value":"26"},{"label":"Premium ghee 10 Ltr","value":"27"},{"label":"Nanak Ghee 20 Ltr","value":"28"},{"label":"Restaurant ghee 10 Ltr","value":"29"}]