[{"label":"Sliced Mushroom","value":"1"},{"label":"Two Fruit","value":"2"},{"label":"Mango Pulp","value":"3"},{"label":"Shezwan chutney","value":"4"},{"label":"Champignon","value":"5"},{"label":"Nanak Ghee","value":"6"},{"label":"Restaurant Ghee","value":"7"},{"label":"Premium Ghee","value":"8"},{"label":"GRB Ghee","value":"9"},{"label":"Rasmalai Bikano","value":"10"},{"label":"Sugar Coated fennel Seed indya","value":"11"},{"label":"Hing Powder mothers","value":"12"},{"label":"Corn Flour 25 kg","value":"13"},{"label":"Corn Flour 1 kg","value":"14"},{"label":"Baking Powder","value":"15"},{"label":"Fried Onion mothers","value":"16"}]